README.md
setup.py
src/__init__.py
src/__main__.py
src/apiclient.py
src/configurator.py
src/converter.py
src/filedto.py
src/filereader.py
src/html_escape_utils.py
src/importer.py
src/minioreader.py
src/parser.py
src/rabbitmq.py
src/reader.py
src/../connection_config.ini
src/models/__init__.py
src/models/link.py
src/models/link_type.py
src/models/step_result.py
src/models/test_result.py
testit_importer_allure.egg-info/PKG-INFO
testit_importer_allure.egg-info/SOURCES.txt
testit_importer_allure.egg-info/dependency_links.txt
testit_importer_allure.egg-info/entry_points.txt
testit_importer_allure.egg-info/requires.txt
testit_importer_allure.egg-info/top_level.txt