Metadata-Version: 2.4
Name: testit-importer-allure
Version: 1.15.0.post560
Summary: Allure report importer for Test IT
Home-page: https://pypi.org/project/testit-importer-allure/
Author: Integration team
Author-email: integrations@testit.software
License: Apache-2.0
Classifier: Programming Language :: Python :: 3
Classifier: Programming Language :: Python :: 3.6
Classifier: Programming Language :: Python :: 3.7
Classifier: Programming Language :: Python :: 3.8
Classifier: Programming Language :: Python :: 3.9
Classifier: Programming Language :: Python :: 3.10
Classifier: Programming Language :: Python :: 3.11
Classifier: Programming Language :: Python :: 3.12
Requires-Dist: testit-api-client==7.4.0.post560
Requires-Dist: xmltodict
Requires-Dist: minio
Requires-Dist: pika
Dynamic: author
Dynamic: author-email
Dynamic: classifier
Dynamic: description
Dynamic: description-content-type
Dynamic: home-page
Dynamic: license
Dynamic: requires-dist
Dynamic: summary
